rotalabs_eval/__init__.py
rotalabs_eval/_version.py
rotalabs_eval/agents/__init__.py
rotalabs_eval/agents/debate.py
rotalabs_eval/agents/tool_use.py
rotalabs_eval/agents/trajectory.py
rotalabs_eval/cache/__init__.py
rotalabs_eval/cache/config.py
rotalabs_eval/cache/disk.py
rotalabs_eval/cache/memory.py
rotalabs_eval/core/__init__.py
rotalabs_eval/core/config.py
rotalabs_eval/core/dataset.py
rotalabs_eval/core/exceptions.py
rotalabs_eval/core/result.py
rotalabs_eval/core/task.py
rotalabs_eval/core/types.py
rotalabs_eval/inference/__init__.py
rotalabs_eval/inference/base.py
rotalabs_eval/inference/batch.py
rotalabs_eval/inference/ollama.py
rotalabs_eval/inference/openai.py
rotalabs_eval/inference/rate_limiter.py
rotalabs_eval/metrics/__init__.py
rotalabs_eval/metrics/base.py
rotalabs_eval/metrics/custom.py
rotalabs_eval/metrics/lexical.py
rotalabs_eval/metrics/llm_judge.py
rotalabs_eval/metrics/rag.py
rotalabs_eval/metrics/registry.py
rotalabs_eval/metrics/semantic.py
rotalabs_eval/orchestrator/__init__.py
rotalabs_eval/orchestrator/async_executor.py
rotalabs_eval/orchestrator/base.py
rotalabs_eval/orchestrator/dask.py
rotalabs_eval/orchestrator/local.py
rotalabs_eval/orchestrator/ray.py
rotalabs_eval/orchestrator/spark.py
rotalabs_eval/reporting/__init__.py
rotalabs_eval/reporting/html.py
rotalabs_eval/reporting/results.py
rotalabs_eval/reporting/viz.py
rotalabs_eval/statistics/__init__.py
rotalabs_eval/statistics/confidence.py
rotalabs_eval/statistics/effect_size.py
rotalabs_eval/statistics/power.py
rotalabs_eval/statistics/significance.py
rotalabs_eval/tracking/__init__.py
rotalabs_eval/tracking/mlflow.py
rotalabs_eval/tracking/wandb.py
rotalabs_eval/utils/__init__.py
rotalabs_eval/utils/cost.py
rotalabs_eval/utils/helpers.py
rotalabs_eval/utils/tiktoken_cache.py
rotalabs_eval-1.0.0.dist-info/METADATA
rotalabs_eval-1.0.0.dist-info/WHEEL
rotalabs_eval-1.0.0.dist-info/licenses/LICENSE
rotalabs_eval-1.0.0.dist-info/RECORD
