Metadata-Version: 2.4
Name: rotalabs-eval
Version: 1.0.0
Summary: Comprehensive LLM evaluation framework with statistical rigor
Project-URL: Homepage, https://rotalabs.ai
Project-URL: Repository, https://github.com/rotalabs/rotalabs-eval
Project-URL: Documentation, https://rotalabs.github.io/rotalabs-eval
Author-email: Subhadip Mitra <subhadip@rotalabs.ai>, Rotalabs Research <research@rotalabs.ai>
License-Expression: AGPL-3.0-or-later
License-File: LICENSE
Keywords: ai,benchmarking,evaluation,llm,metrics,statistical-testing
Classifier: Development Status :: 4 - Beta
Classifier: Intended Audience :: Developers
Classifier: Intended Audience :: Science/Research
Classifier: License :: OSI Approved :: GNU Affero General Public License v3 or later (AGPLv3+)
Classifier: Programming Language :: Python :: 3
Classifier: Programming Language :: Python :: 3.9
Classifier: Programming Language :: Python :: 3.10
Classifier: Programming Language :: Python :: 3.11
Classifier: Programming Language :: Python :: 3.12
Classifier: Topic :: Scientific/Engineering :: Artificial Intelligence
Requires-Python: >=3.9
Requires-Dist: numpy>=1.24.0
Requires-Dist: pandas>=2.0.0
Requires-Dist: pyyaml>=6.0
Requires-Dist: requests>=2.28.0
Requires-Dist: scikit-learn>=1.3.0
Requires-Dist: scipy>=1.10.0
Requires-Dist: tiktoken>=0.5.0
Requires-Dist: tqdm>=4.65.0
Provides-Extra: all
Requires-Dist: dask[distributed]>=2023.1.0; extra == 'all'
Requires-Dist: matplotlib>=3.7.0; extra == 'all'
Requires-Dist: mlflow>=2.8.0; extra == 'all'
Requires-Dist: ollama>=0.1.0; extra == 'all'
Requires-Dist: openai>=1.0.0; extra == 'all'
Requires-Dist: plotly>=5.15.0; extra == 'all'
Requires-Dist: pyspark>=3.4.0; extra == 'all'
Requires-Dist: ray>=2.8.0; extra == 'all'
Requires-Dist: seaborn>=0.12.0; extra == 'all'
Requires-Dist: sentence-transformers>=2.2.0; extra == 'all'
Requires-Dist: wandb>=0.16.0; extra == 'all'
Provides-Extra: dask
Requires-Dist: dask[distributed]>=2023.1.0; extra == 'dask'
Provides-Extra: dev
Requires-Dist: black>=23.0.0; extra == 'dev'
Requires-Dist: mypy>=1.5.0; extra == 'dev'
Requires-Dist: pytest-asyncio>=0.21.0; extra == 'dev'
Requires-Dist: pytest-cov>=4.1.0; extra == 'dev'
Requires-Dist: pytest>=7.4.0; extra == 'dev'
Requires-Dist: ruff>=0.1.0; extra == 'dev'
Provides-Extra: embeddings
Requires-Dist: sentence-transformers>=2.2.0; extra == 'embeddings'
Provides-Extra: ollama
Requires-Dist: ollama>=0.1.0; extra == 'ollama'
Provides-Extra: openai
Requires-Dist: openai>=1.0.0; extra == 'openai'
Provides-Extra: ray
Requires-Dist: ray>=2.8.0; extra == 'ray'
Provides-Extra: spark
Requires-Dist: pyspark>=3.4.0; extra == 'spark'
Provides-Extra: tracking
Requires-Dist: mlflow>=2.8.0; extra == 'tracking'
Provides-Extra: viz
Requires-Dist: matplotlib>=3.7.0; extra == 'viz'
Requires-Dist: plotly>=5.15.0; extra == 'viz'
Requires-Dist: seaborn>=0.12.0; extra == 'viz'
Provides-Extra: wandb
Requires-Dist: wandb>=0.16.0; extra == 'wandb'
